{"11":{"initialTime":"16:00","price":23000.0,"name":"Peluqueria","isForGroup":false,"daysAvailable":["MONDAY","THURSDAY","WEDNESDAY","TUESDAY","FRIDAY"],"id":"11","finalTime":"21:00"},"1":{"initialTime":"15:00","price":130000.0,"name":"SPA","isForGroup":false,"daysAvailable":["SATURDAY","SUNDAY"],"id":"1","finalTime":"20:00"},"2":{"initialTime":"08:00","price":600000.0,"name":"Traslado al aeropuerto","isForGroup":true,"daysAvailable":["MONDAY","TUESDAY","WEDNESDAY","THURSDAY","FRIDAY","SATURDAY","SUNDAY"],"id":"2","finalTime":"22:00"},"3":{"initialTime":"09:00","price":50000.0,"name":"Clases de yoga","isForGroup":false,"daysAvailable":["MONDAY","WEDNESDAY","FRIDAY"],"id":"3","finalTime":"10:30"},"4":{"initialTime":"08:00","price":40000.0,"name":"Servicio de lavandería","isForGroup":false,"daysAvailable":["MONDAY","TUESDAY","WEDNESDAY","THURSDAY","FRIDAY","SATURDAY","SUNDAY"],"id":"4","finalTime":"18:00"},"5":{"initialTime":"10:00","price":90000.0,"name":"Servicio de masajes","isForGroup":false,"daysAvailable":["MONDAY","TUESDAY","WEDNESDAY","THURSDAY","FRIDAY","SATURDAY","SUNDAY"],"id":"5","finalTime":"21:00"},"6":{"initialTime":"07:00","price":60000.0,"name":"Servicio de alquiler de bicicletas","isForGroup":true,"daysAvailable":["MONDAY","TUESDAY","WEDNESDAY","THURSDAY","FRIDAY","SATURDAY","SUNDAY"],"id":"6","finalTime":"20:00"},"7":{"initialTime":"09:00","price":150000.0,"name":"Tour guiado por la ciudad","isForGroup":true,"daysAvailable":["SATURDAY","SUNDAY"],"id":"7","finalTime":"13:00"},"8":{"initialTime":"10:00","price":70000.0,"name":"Servicio de niñera","isForGroup":false,"daysAvailable":["MONDAY","TUESDAY","WEDNESDAY","THURSDAY","FRIDAY","SATURDAY","SUNDAY"],"id":"8","finalTime":"20:00"},"9":{"initialTime":"10:00","price":40000.0,"name":"Sala de juegos","isForGroup":true,"daysAvailable":["MONDAY","TUESDAY","WEDNESDAY","THURSDAY","FRIDAY","SATURDAY","SUNDAY"],"id":"9","finalTime":"22:00"},"10":{"initialTime":"08:00","price":200000.0,"name":"Servicio de alquiler de coches","isForGroup":false,"daysAvailable":["MONDAY","TUESDAY","WEDNESDAY","THURSDAY","FRIDAY","SATURDAY","SUNDAY"],"id":"10","finalTime":"20:00"}}